aiohttp/__init__.py
aiohttp/_cookie_helpers.py
aiohttp/_cparser.pxd
aiohttp/_find_header.pxd
aiohttp/_headers.pxi
aiohttp/_http_parser.cpython-311-aarch64-linux-gnu.so
aiohttp/_http_parser.pyx
aiohttp/_http_writer.cpython-311-aarch64-linux-gnu.so
aiohttp/_http_writer.pyx
aiohttp/abc.py
aiohttp/base_protocol.py
aiohttp/client.py
aiohttp/client_exceptions.py
aiohttp/client_middleware_digest_auth.py
aiohttp/client_middlewares.py
aiohttp/client_proto.py
aiohttp/client_reqrep.py
aiohttp/client_ws.py
aiohttp/compression_utils.py
aiohttp/connector.py
aiohttp/cookiejar.py
aiohttp/formdata.py
aiohttp/hdrs.py
aiohttp/helpers.py
aiohttp/http.py
aiohttp/http_exceptions.py
aiohttp/http_parser.py
aiohttp/http_websocket.py
aiohttp/http_writer.py
aiohttp/log.py
aiohttp/multipart.py
aiohttp/payload.py
aiohttp/payload_streamer.py
aiohttp/py.typed
aiohttp/pytest_plugin.py
aiohttp/resolver.py
aiohttp/streams.py
aiohttp/tcp_helpers.py
aiohttp/test_utils.py
aiohttp/tracing.py
aiohttp/typedefs.py
aiohttp/web.py
aiohttp/web_app.py
aiohttp/web_exceptions.py
aiohttp/web_fileresponse.py
aiohttp/web_log.py
aiohttp/web_middlewares.py
aiohttp/web_protocol.py
aiohttp/web_request.py
aiohttp/web_response.py
aiohttp/web_routedef.py
aiohttp/web_runner.py
aiohttp/web_server.py
aiohttp/web_urldispatcher.py
aiohttp/web_ws.py
aiohttp/worker.py
aiohttp/.hash/_cparser.pxd.hash
aiohttp/.hash/_find_header.pxd.hash
aiohttp/.hash/_http_parser.pyx.hash
aiohttp/.hash/_http_writer.pyx.hash
aiohttp/.hash/hdrs.py.hash
aiohttp/_websocket/__init__.py
aiohttp/_websocket/helpers.py
aiohttp/_websocket/mask.cpython-311-aarch64-linux-gnu.so
aiohttp/_websocket/mask.pxd
aiohttp/_websocket/mask.pyx
aiohttp/_websocket/models.py
aiohttp/_websocket/reader.py
aiohttp/_websocket/reader_c.cpython-311-aarch64-linux-gnu.so
aiohttp/_websocket/reader_c.pxd
aiohttp/_websocket/reader_c.py
aiohttp/_websocket/reader_py.py
aiohttp/_websocket/writer.py
aiohttp-3.12.11.dist-info/METADATA
aiohttp-3.12.11.dist-info/WHEEL
aiohttp-3.12.11.dist-info/top_level.txt
aiohttp-3.12.11.dist-info/RECORD
aiohttp-3.12.11.dist-info/licenses/LICENSE.txt
