Metadata-Version: 2.4
Name: aiohttp
Version: 3.12.11
Summary: Async http client/server framework (asyncio)
Home-page: https://github.com/aio-libs/aiohttp
Maintainer: aiohttp team <team@aiohttp.org>
Maintainer-email: team@aiohttp.org
License: Apache-2.0
Project-URL: Chat: Matrix, https://matrix.to/#/#aio-libs:matrix.org
Project-URL: Chat: Matrix Space, https://matrix.to/#/#aio-libs-space:matrix.org
Project-URL: CI: GitHub Actions, https://github.com/aio-libs/aiohttp/actions?query=workflow%3ACI
Project-URL: Coverage: codecov, https://codecov.io/github/aio-libs/aiohttp
Project-URL: Docs: Changelog, https://docs.aiohttp.org/en/stable/changes.html
Project-URL: Docs: RTD, https://docs.aiohttp.org
Project-URL: GitHub: issues, https://github.com/aio-libs/aiohttp/issues
Project-URL: GitHub: repo, https://github.com/aio-libs/aiohttp
Classifier: Development Status :: 5 - Production/Stable
Classifier: Framework :: AsyncIO
Classifier: Intended Audience :: Developers
Classifier: Operating System :: POSIX
Classifier: Operating System :: MacOS :: MacOS X
Classifier: Operating System :: Microsoft :: Windows
Classifier: Programming Language :: Python
Classifier: Programming Language :: Python :: 3
Classifier: Programming Language :: Python :: 3.9
Classifier: Programming Language :: Python :: 3.10
Classifier: Programming Language :: Python :: 3.11
Classifier: Programming Language :: Python :: 3.12
Classifier: Programming Language :: Python :: 3.13
Classifier: Topic :: Internet :: WWW/HTTP
Requires-Python: >=3.9
License-File: LICENSE.txt
Requires-Dist: aiohappyeyeballs>=2.5.0
Requires-Dist: aiosignal>=1.1.2
Requires-Dist: async-timeout<6.0,>=4.0; python_version < "3.11"
Requires-Dist: attrs>=17.3.0
Requires-Dist: frozenlist>=1.1.1
Requires-Dist: multidict<7.0,>=4.5
Requires-Dist: propcache>=0.2.0
Requires-Dist: yarl<2.0,>=1.17.0
Provides-Extra: speedups
Requires-Dist: aiodns>=3.3.0; extra == "speedups"
Requires-Dist: Brotli; platform_python_implementation == "CPython" and extra == "speedups"
Requires-Dist: brotlicffi; platform_python_implementation != "CPython" and extra == "speedups"
Dynamic: license-file
